odoo9_addon_mail_thread_medical_prescription-9.0.1.0.0-py2.7-nspkg.pth
odoo_addons/mail_thread_medical_prescription/__openerp__.py
odoo_addons/mail_thread_medical_prescription/__init__.py
odoo_addons/mail_thread_medical_prescription/README.rst
odoo_addons/mail_thread_medical_prescription/models/medical_prescription_order.py
odoo_addons/mail_thread_medical_prescription/models/medical_prescription_order_line.py
odoo_addons/mail_thread_medical_prescription/models/__init__.py
odoo_addons/mail_thread_medical_prescription/views/medical_prescription_order_line_view.xml
odoo_addons/mail_thread_medical_prescription/views/medical_prescription_order_view.xml
odoo_addons/mail_thread_medical_prescription/tests/__init__.py
odoo_addons/mail_thread_medical_prescription/tests/test_prescription_order_line.py
odoo_addons/mail_thread_medical_prescription/tests/test_prescription_order.py
odoo_addons/mail_thread_medical_prescription/static/description/icon.png
odoo9_addon_mail_thread_medical_prescription-9.0.1.0.0.dist-info/top_level.txt
odoo9_addon_mail_thread_medical_prescription-9.0.1.0.0.dist-info/WHEEL
odoo9_addon_mail_thread_medical_prescription-9.0.1.0.0.dist-info/RECORD
odoo9_addon_mail_thread_medical_prescription-9.0.1.0.0.dist-info/metadata.json
odoo9_addon_mail_thread_medical_prescription-9.0.1.0.0.dist-info/DESCRIPTION.rst
odoo9_addon_mail_thread_medical_prescription-9.0.1.0.0.dist-info/METADATA
odoo9_addon_mail_thread_medical_prescription-9.0.1.0.0.dist-info/namespace_packages.txt
